qushiqyukla.py
qushiqyukla-0.1.0.dist-info/WHEEL
qushiqyukla-0.1.0.dist-info/METADATA
qushiqyukla-0.1.0.dist-info/RECORD
