Metadata-Version: 2.1
Name: qushiqyukla
Version: 0.1.0
Summary: qo'shiqni yuklab oladiga modul
Author: Xumoyun Rayimov
Requires-Python: >=3.10,<4.0
Classifier: Programming Language :: Python :: 3
Classifier: Programming Language :: Python :: 3.10
